pyslit.py
pyslit-3.9.1.dist-info/LICENSE.txt
pyslit-3.9.1.dist-info/METADATA
pyslit-3.9.1.dist-info/WHEEL
pyslit-3.9.1.dist-info/top_level.txt
pyslit-3.9.1.dist-info/RECORD
