Metadata-Version: 2.1
Name: pyslit
Version: 3.9.1
Summary: AI(ChatGPT), AI image creator, Text to speech, Speech recognizer, Music player, Play video on youtube, Google and Wikipedia search, Control the system, News, Datetime,Run cmd commands, All in one perfect module for data types
Author: Ashraq
Author-email: ashraqmohideen@gmail.com
Classifier: Programming Language :: Python :: 3
Classifier: License :: OSI Approved :: MIT License
Classifier: Operating System :: OS Independent
Requires-Python: <=3.10.8
License-File: LICENSE.txt
Requires-Dist: pyttsx3
Requires-Dist: pygame
Requires-Dist: pyaudio
Requires-Dist: SpeechRecognition
Requires-Dist: pywhatkit
Requires-Dist: wikipedia
Requires-Dist: requests
Requires-Dist: datetime
Requires-Dist: bs4
Requires-Dist: openai ==0.28.1
